[{"domain":"second.info","status":"resell","attractiveness":120,"demand":23,"length":6,"created":"2018-06-14T10:06:58.000Z","expires":"2026-06-14T10:06:58.000Z","registrar":"GMO Internet Group, Inc. d/b/a Onamae.com","sectors":"General,Mathematics"},{"domain":"complete.info","status":"resell","attractiveness":120,"demand":21,"length":8,"created":"2014-05-29T10:09:36.000Z","expires":"2026-05-29T10:09:36.000Z","registrar":"Dynadot Inc","sectors":"Manufacturing,Retail,Technology"},{"domain":"tenth.info","status":"available","attractiveness":116,"demand":7,"length":5,"created":"","expires":"","registrar":null,"sectors":"Mathematics"},{"domain":"tonic.info","status":"resell","attractiveness":114,"demand":22,"length":5,"created":"2023-02-16T15:15:56.000Z","expires":"2026-02-16T15:15:56.000Z","registrar":"Sav.com, LLC - 21","sectors":"Health and Fitness,Medicine,Science"},{"domain":"hotshot.info","status":"resell","attractiveness":112,"demand":14,"length":7,"created":"2025-01-11T15:15:37.000Z","expires":"2026-01-11T15:15:37.000Z","registrar":"Sav.com, LLC - 10","sectors":"Business,Entertainment,Sports"},{"domain":"above.info","status":"resell","attractiveness":112,"demand":22,"length":5,"created":"2024-02-11T17:00:00.000Z","expires":"2026-02-11T17:00:00.000Z","registrar":"Netregistry Wholesale Pty Ltd","sectors":"Business"},{"domain":"acute.info","status":"resell","attractiveness":112,"demand":9,"length":5,"created":"2025-02-24T15:15:15.000Z","expires":"2026-02-24T15:15:15.000Z","registrar":"Sav.com, LLC - 31","sectors":"Mathematics,Medicine,Science"},{"domain":"abstract.info","status":"resell","attractiveness":108,"demand":29,"length":8,"created":"2021-03-26T14:31:16.000Z","expires":"2026-03-26T14:31:16.000Z","registrar":"Dynadot7 LLC","sectors":"Arts,Humanities,Science"},{"domain":"teen.info","status":"resell","attractiveness":104,"demand":14,"length":4,"created":"2002-07-13T19:29:10.000Z","expires":"2027-07-13T19:29:10.000Z","registrar":"Dynadot Inc","sectors":"Education,Entertainment,Healthcare"},{"domain":"absent.info","status":"available","attractiveness":102,"demand":8,"length":6,"created":"","expires":"","registrar":null,"sectors":"Business,Education,Technology"},{"domain":"eight.info","status":"expiring","attractiveness":102,"demand":23,"length":5,"created":"2001-09-12T00:52:02.000Z","expires":"2025-09-12T00:52:02.000Z","registrar":"eNom, LLC","sectors":"General,Mathematics"},{"domain":"captive.info","status":"expiring","attractiveness":102,"demand":14,"length":7,"created":"2024-08-20T17:00:06.000Z","expires":"2025-08-20T17:00:06.000Z","registrar":"Sav.com, LLC - 33","sectors":"Entertainment,Hospitality,Technology"},{"domain":"sixth.info","status":"available","attractiveness":100,"demand":8,"length":5,"created":"","expires":"","registrar":null,"sectors":"Mathematics"},{"domain":"abrupt.info","status":"available","attractiveness":100,"demand":3,"length":6,"created":"","expires":"","registrar":null,"sectors":"Medicine,Science"},{"domain":"ninth.info","status":"available","attractiveness":100,"demand":9,"length":5,"created":"","expires":"","registrar":null,"sectors":"Mathematics"},{"domain":"eighth.info","status":"available","attractiveness":100,"demand":6,"length":6,"created":"","expires":"","registrar":null,"sectors":"Mathematics"},{"domain":"forgiving.info","status":"available","attractiveness":96,"demand":3,"length":9,"created":"","expires":"","registrar":null,"sectors":"Healthcare,Religion"},{"domain":"academic.info","status":"resell","attractiveness":96,"demand":20,"length":8,"created":"2002-07-13T19:57:39.000Z","expires":"2027-07-13T19:57:39.000Z","registrar":"Dynadot Inc","sectors":"Education,Humanities,Science"},{"domain":"actual.info","status":"premium","attractiveness":96,"demand":22,"length":6,"created":"2021-07-09T14:30:37.000Z","expires":"2026-07-09T14:30:37.000Z","registrar":"Squarespace Domains II LLC","sectors":"Real Estate,Retail,Technology"},{"domain":"adequate.info","status":"resell","attractiveness":94,"demand":9,"length":8,"created":"2024-10-10T02:31:24.000Z","expires":"2025-10-10T02:31:24.000Z","registrar":"Dynadot Inc","sectors":"Education,Healthcare,Technology"},{"domain":"virtuoso.info","status":"resell","attractiveness":94,"demand":16,"length":8,"created":"2025-03-14T15:15:43.000Z","expires":"2026-03-14T15:15:43.000Z","registrar":"Sav.com, LLC - 4","sectors":"Arts,Entertainment"},{"domain":"abject.info","status":"available","attractiveness":94,"demand":7,"length":6,"created":"","expires":"","registrar":null,"sectors":"Humanities"},{"domain":"around.info","status":"resell","attractiveness":94,"demand":22,"length":6,"created":"2004-10-20T09:43:22.000Z","expires":"2026-10-20T09:43:22.000Z","registrar":"InterNetX GmbH","sectors":"Business,General,Media,Technology"},{"domain":"exemplary.info","status":"resell","attractiveness":92,"demand":5,"length":9,"created":"2024-12-30T15:56:39.000Z","expires":"2025-12-30T15:56:39.000Z","registrar":"Alibaba Cloud Computing Ltd. d/b/a HiChina (www.net.cn)","sectors":"Business,Education,Healthcare"},{"domain":"adept.info","status":"resell","attractiveness":92,"demand":24,"length":5,"created":"2023-11-08T17:00:01.000Z","expires":"2025-11-08T17:00:01.000Z","registrar":"Sav.com, LLC - 34","sectors":"Education,Health and Fitness,Sports"},{"domain":"nought.info","status":"available","attractiveness":92,"demand":4,"length":6,"created":"","expires":"","registrar":null,"sectors":"Mathematics"},{"domain":"abroad.info","status":"resell","attractiveness":92,"demand":12,"length":6,"created":"2001-09-14T00:50:08.000Z","expires":"2026-09-14T00:50:08.000Z","registrar":"Epik LLC","sectors":"Hospitality,Travel"},{"domain":"twentieth.info","status":"available","attractiveness":92,"demand":3,"length":9,"created":"","expires":"","registrar":null,"sectors":"Mathematics"},{"domain":"addictive.info","status":"premium","attractiveness":90,"demand":9,"length":9,"created":"2005-02-15T09:40:41.000Z","expires":"2026-02-15T09:40:41.000Z","registrar":"Sea Wasp, LLC","sectors":"Healthcare"},{"domain":"endearing.info","status":"available","attractiveness":90,"demand":1,"length":9,"created":"","expires":"","registrar":null,"sectors":"Entertainment,Fashion,Retail"},{"domain":"abortive.info","status":"available","attractiveness":90,"demand":1,"length":8,"created":"","expires":"","registrar":null,"sectors":"Medicine,Science"},{"domain":"gripping.info","status":"available","attractiveness":90,"demand":3,"length":8,"created":"","expires":"","registrar":null,"sectors":"Entertainment,Media,Technology"},{"domain":"riveting.info","status":"resell","attractiveness":90,"demand":6,"length":8,"created":"2024-12-30T16:57:21.000Z","expires":"2025-12-30T16:57:21.000Z","registrar":"Alibaba Cloud Computing Ltd. d/b/a HiChina (www.net.cn)","sectors":"Entertainment,Media,Technology"},{"domain":"additional.info","status":"resell","attractiveness":90,"demand":8,"length":10,"created":"2003-11-28T21:51:13.000Z","expires":"2025-11-28T21:51:13.000Z","registrar":"Sea Wasp, LLC","sectors":"Fashion,Retail,Technology"},{"domain":"adlib.info","status":"available","attractiveness":88,"demand":7,"length":6,"created":"","expires":"","registrar":null,"sectors":"Entertainment"},{"domain":"wide.info","status":"resell","attractiveness":88,"demand":18,"length":4,"created":"2025-02-25T15:15:41.000Z","expires":"2026-02-25T15:15:41.000Z","registrar":"Sav.com, LLC - 32","sectors":"Business,Media,Technology"},{"domain":"activist.info","status":"resell","attractiveness":88,"demand":12,"length":8,"created":"2003-12-18T05:47:28.000Z","expires":"2025-12-18T05:47:28.000Z","registrar":"GoDaddy.com, LLC","sectors":"Humanities,Politics"},{"domain":"sixteen.info","status":"resell","attractiveness":88,"demand":10,"length":7,"created":"2024-12-08T17:00:01.000Z","expires":"2025-12-08T17:00:01.000Z","registrar":"Sav.com, LLC - 47","sectors":"Mathematics"},{"domain":"eleven.info","status":"expiring","attractiveness":88,"demand":32,"length":6,"created":"2001-09-22T08:03:59.000Z","expires":"2025-09-22T08:03:59.000Z","registrar":"Mesh Digital Limited","sectors":"Mathematics"},{"domain":"proficient.info","status":"resell","attractiveness":88,"demand":8,"length":10,"created":"2014-05-06T15:51:35.000Z","expires":"2026-05-06T15:51:35.000Z","registrar":"GoDaddy.com, LLC","sectors":"Education,Health and Fitness,Sports"},{"domain":"twelve.info","status":"resell","attractiveness":88,"demand":18,"length":6,"created":"2022-11-25T15:15:56.000Z","expires":"2025-11-25T15:15:56.000Z","registrar":"IHS Telekom, Inc.","sectors":"General,Mathematics"},{"domain":"hundred.info","status":"resell","attractiveness":88,"demand":13,"length":7,"created":"2016-06-27T10:40:24.000Z","expires":"2026-06-27T10:40:24.000Z","registrar":"GMO Internet Group, Inc. d/b/a Onamae.com","sectors":"Mathematics"},{"domain":"fifteen.info","status":"resell","attractiveness":88,"demand":13,"length":7,"created":"2024-09-29T17:00:02.000Z","expires":"2025-09-29T17:00:02.000Z","registrar":"Sav.com, LLC - 46","sectors":"Mathematics"},{"domain":"recondite.info","status":"available","attractiveness":86,"demand":4,"length":9,"created":"","expires":"","registrar":null,"sectors":"Arts,Humanities,Science"},{"domain":"attendant.info","status":"resell","attractiveness":86,"demand":5,"length":9,"created":"2014-07-12T15:03:45.000Z","expires":"2026-07-12T15:03:45.000Z","registrar":"NameSilo, LLC","sectors":"Healthcare,Hospitality,Transportation"},{"domain":"engrossing.info","status":"available","attractiveness":86,"demand":0,"length":10,"created":"","expires":"","registrar":null,"sectors":"Entertainment,Media,Technology"},{"domain":"xiv.info","status":"resell","attractiveness":86,"demand":12,"length":3,"created":"2025-05-23T15:15:41.000Z","expires":"2026-05-23T15:15:41.000Z","registrar":"Sav.com, LLC - 2","sectors":"Mathematics"},{"domain":"extempore.info","status":"expiring","attractiveness":86,"demand":3,"length":9,"created":"2013-09-12T09:04:26.000Z","expires":"2025-09-12T09:04:26.000Z","registrar":"PDR Ltd. d/b/a PublicDomainRegistry.com","sectors":"Entertainment"},{"domain":"intent.info","status":"resell","attractiveness":86,"demand":25,"length":6,"created":"2024-03-01T17:00:01.000Z","expires":"2026-03-01T17:00:01.000Z","registrar":"Netregistry Wholesale Pty Ltd","sectors":"Business,Education,Technology"},{"domain":"adolescent.info","status":"expiring","attractiveness":86,"demand":3,"length":10,"created":"2001-09-15T18:14:23.000Z","expires":"2025-09-15T18:14:23.000Z","registrar":"NameSecure L.L.C.","sectors":"Education,Entertainment,Healthcare"},{"domain":"star.info","status":"resell","attractiveness":86,"demand":40,"length":4,"created":"2002-07-13T19:29:25.000Z","expires":"2026-07-13T19:29:25.000Z","registrar":"GoDaddy.com, LLC","sectors":"Entertainment,Media,Sports"},{"domain":"thousand.info","status":"resell","attractiveness":84,"demand":8,"length":8,"created":"2013-02-15T13:42:25.000Z","expires":"2026-02-15T13:42:25.000Z","registrar":"GoDaddy.com, LLC","sectors":"Mathematics"},{"domain":"adjustable.info","status":"available","attractiveness":84,"demand":3,"length":10,"created":"","expires":"","registrar":null,"sectors":"Manufacturing,Retail,Technology"},{"domain":"seventeen.info","status":"expiring","attractiveness":84,"demand":7,"length":9,"created":"2012-09-03T10:10:37.000Z","expires":"2025-09-03T10:10:37.000Z","registrar":"NameCheap, Inc.","sectors":"Mathematics"},{"domain":"fourteen.info","status":"resell","attractiveness":84,"demand":8,"length":8,"created":"2024-12-30T11:44:10.000Z","expires":"2025-12-30T11:44:10.000Z","registrar":"Alibaba Cloud Computing Ltd. d/b/a HiChina (www.net.cn)","sectors":"Mathematics"},{"domain":"twentyone.info","status":"resell","attractiveness":84,"demand":13,"length":10,"created":"2025-08-06T15:16:03.000Z","expires":"2026-08-06T15:16:03.000Z","registrar":"Sav.com, LLC - 8","sectors":"Mathematics"},{"domain":"accessory.info","status":"expiring","attractiveness":84,"demand":8,"length":9,"created":"2015-09-17T10:05:10.000Z","expires":"2025-09-17T10:05:10.000Z","registrar":"Dynadot Inc","sectors":"Fashion,Retail,Technology"},{"domain":"twentytwo.info","status":"resell","attractiveness":84,"demand":10,"length":10,"created":"2025-05-09T15:15:40.000Z","expires":"2026-05-09T15:15:40.000Z","registrar":"Sav.com, LLC - 29","sectors":"Mathematics"},{"domain":"grand.info","status":"resell","attractiveness":84,"demand":25,"length":5,"created":"2004-11-27T09:53:24.000Z","expires":"2025-11-27T09:53:24.000Z","registrar":"Dynadot Inc","sectors":"Finance,General"},{"domain":"thirteen.info","status":"resell","attractiveness":84,"demand":10,"length":8,"created":"2024-12-07T17:00:04.000Z","expires":"2025-12-07T17:00:04.000Z","registrar":"Sav.com, LLC - 47","sectors":"Mathematics"},{"domain":"acting.info","status":"resell","attractiveness":84,"demand":12,"length":6,"created":"2002-07-13T19:34:59.000Z","expires":"2026-07-13T19:34:59.000Z","registrar":"GoDaddy.com, LLC","sectors":"Entertainment"},{"domain":"nineteen.info","status":"resell","attractiveness":84,"demand":8,"length":8,"created":"2025-05-10T19:38:31.000Z","expires":"2026-05-10T19:38:31.000Z","registrar":"Dynadot Inc","sectors":"Mathematics"},{"domain":"impromptu.info","status":"resell","attractiveness":82,"demand":16,"length":9,"created":"2024-11-19T22:02:03.000Z","expires":"2025-11-19T22:02:03.000Z","registrar":"Spaceship, Inc.","sectors":"Entertainment"},{"domain":"absorbent.info","status":"available","attractiveness":82,"demand":3,"length":9,"created":"","expires":"","registrar":null,"sectors":"Healthcare,Manufacturing,Retail"},{"domain":"abenaki.info","status":"available","attractiveness":82,"demand":2,"length":7,"created":"","expires":"","registrar":null,"sectors":"Geography"},{"domain":"abroach.info","status":"available","attractiveness":82,"demand":1,"length":7,"created":"","expires":"","registrar":null,"sectors":"Food and Beverage"},{"domain":"dozen.info","status":"expiring","attractiveness":82,"demand":10,"length":5,"created":"2001-09-18T05:12:31.000Z","expires":"2025-09-18T05:12:31.000Z","registrar":"Hosting Concepts B.V. d/b/a Registrar.eu","sectors":"Mathematics"},{"domain":"abdominal.info","status":"available","attractiveness":82,"demand":1,"length":9,"created":"","expires":"","registrar":null,"sectors":"Health and Fitness,Medicine"},{"domain":"fivesome.info","status":"available","attractiveness":82,"demand":1,"length":8,"created":"","expires":"","registrar":null,"sectors":"Sports"},{"domain":"abkhaz.info","status":"available","attractiveness":82,"demand":1,"length":6,"created":"","expires":"","registrar":null,"sectors":"Geography"},{"domain":"decade.info","status":"resell","attractiveness":82,"demand":10,"length":6,"created":"2025-02-08T15:15:14.000Z","expires":"2026-02-08T15:15:14.000Z","registrar":"Sav.com, LLC - 5","sectors":"Mathematics"},{"domain":"absorbable.info","status":"available","attractiveness":80,"demand":0,"length":10,"created":"","expires":"","registrar":null,"sectors":"Healthcare,Pharmaceuticals,Science"},{"domain":"worshipful.info","status":"available","attractiveness":80,"demand":1,"length":10,"created":"","expires":"","registrar":null,"sectors":"Education,Healthcare,Religion"},{"domain":"twenty.info","status":"resell","attractiveness":80,"demand":12,"length":6,"created":"2024-10-05T17:00:01.000Z","expires":"2025-10-05T17:00:01.000Z","registrar":"Sav.com, LLC - 47","sectors":"Mathematics"},{"domain":"forty.info","status":"resell","attractiveness":80,"demand":9,"length":5,"created":"2025-01-11T15:15:33.000Z","expires":"2026-01-11T15:15:33.000Z","registrar":"Sav.com, LLC - 4","sectors":"Mathematics"},{"domain":"absolute.info","status":"resell","attractiveness":80,"demand":25,"length":8,"created":"2017-03-05T10:35:29.000Z","expires":"2026-03-05T10:35:29.000Z","registrar":"Sav.com, LLC","sectors":"Engineering,Mathematics,Science"},{"domain":"abundant.info","status":"available","attractiveness":80,"demand":19,"length":8,"created":"","expires":"","registrar":null,"sectors":"Agriculture,Manufacturing,Retail"},{"domain":"absurd.info","status":"resell","attractiveness":80,"demand":16,"length":6,"created":"2023-10-19T17:00:00.000Z","expires":"2025-10-19T17:00:00.000Z","registrar":"Sav.com, LLC - 8","sectors":"Arts,Entertainment,Media"},{"domain":"nine.info","status":"expiring","attractiveness":80,"demand":24,"length":4,"created":"2001-09-12T00:57:23.000Z","expires":"2025-09-12T00:57:23.000Z","registrar":"eNom, LLC","sectors":"General,Mathematics"},{"domain":"sequent.info","status":"resell","attractiveness":80,"demand":7,"length":7,"created":"2024-12-30T14:55:48.000Z","expires":"2025-12-30T14:55:48.000Z","registrar":"Alibaba Cloud Computing Ltd. d/b/a HiChina (www.net.cn)","sectors":"Healthcare,Insurance,Transportation"},{"domain":"seventh.info","status":"resell","attractiveness":80,"demand":10,"length":7,"created":"2025-04-11T15:15:09.000Z","expires":"2026-04-11T15:15:09.000Z","registrar":"Sav.com, LLC - 33","sectors":"Mathematics"},{"domain":"superstar.info","status":"resell","attractiveness":80,"demand":18,"length":9,"created":"2001-07-31T16:15:47.000Z","expires":"2026-07-31T16:15:47.000Z","registrar":"GoDaddy.com, LLC","sectors":"Entertainment"},{"domain":"abkhasian.info","status":"available","attractiveness":78,"demand":1,"length":9,"created":"","expires":"","registrar":null,"sectors":"Geography"},{"domain":"abkhazian.info","status":"available","attractiveness":78,"demand":1,"length":9,"created":"","expires":"","registrar":null,"sectors":"Geography"},{"domain":"dormant.info","status":"available","attractiveness":78,"demand":4,"length":7,"created":"","expires":"","registrar":null,"sectors":"Medicine,Science"},{"domain":"acceptant.info","status":"available","attractiveness":78,"demand":1,"length":9,"created":"","expires":"","registrar":null,"sectors":"Education,Healthcare"},{"domain":"acceptable.info","status":"available","attractiveness":78,"demand":5,"length":10,"created":"","expires":"","registrar":null,"sectors":"Business,Hospitality,Retail"},{"domain":"adorable.info","status":"resell","attractiveness":78,"demand":8,"length":8,"created":"2025-02-21T15:15:56.000Z","expires":"2026-02-21T15:15:56.000Z","registrar":"Sav.com, LLC - 44","sectors":"Entertainment,Fashion,Retail"},{"domain":"athletic.info","status":"resell","attractiveness":78,"demand":15,"length":8,"created":"2011-12-04T10:11:27.000Z","expires":"2025-12-04T10:11:27.000Z","registrar":"GoDaddy.com, LLC","sectors":"Health and Fitness,Sports"},{"domain":"recognised.info","status":"available","attractiveness":78,"demand":3,"length":10,"created":"","expires":"","registrar":null,"sectors":"Business,Education,Technology"},{"domain":"low.info","status":"resell","attractiveness":78,"demand":20,"length":3,"created":"2024-10-19T15:15:41.000Z","expires":"2025-10-19T15:15:41.000Z","registrar":"Sav.com, LLC - 10","sectors":"Business,Finance"},{"domain":"accidental.info","status":"available","attractiveness":78,"demand":11,"length":10,"created":"","expires":"","registrar":null,"sectors":"Healthcare,Insurance,Transportation"},{"domain":"absorptive.info","status":"available","attractiveness":78,"demand":1,"length":10,"created":"","expires":"","registrar":null,"sectors":"Healthcare,Manufacturing,Retail"},{"domain":"accepted.info","status":"resell","attractiveness":78,"demand":6,"length":8,"created":"2025-03-22T17:00:12.000Z","expires":"2026-03-22T17:00:12.000Z","registrar":"Dynadot Inc","sectors":"Business,Education,Technology"},{"domain":"accurate.info","status":"resell","attractiveness":78,"demand":16,"length":8,"created":"2024-12-08T17:00:01.000Z","expires":"2025-12-08T17:00:01.000Z","registrar":"Sav.com, LLC - 39","sectors":"Engineering,Mathematics,Science"},{"domain":"thirteenth.info","status":"available","attractiveness":76,"demand":3,"length":10,"created":"","expires":"","registrar":null,"sectors":"Mathematics"},{"domain":"acoustic.info","status":"expiring","attractiveness":76,"demand":14,"length":8,"created":"2001-09-14T00:05:41.000Z","expires":"2025-09-14T00:05:41.000Z","registrar":"GoDaddy.com, LLC","sectors":"Science"},{"domain":"fifteenth.info","status":"resell","attractiveness":76,"demand":2,"length":9,"created":"2024-10-02T00:01:24.000Z","expires":"2025-10-02T00:01:24.000Z","registrar":"NameCheap, Inc.","sectors":"Mathematics"},{"domain":"hundredth.info","status":"available","attractiveness":76,"demand":1,"length":9,"created":"","expires":"","registrar":null,"sectors":"Mathematics"},{"domain":"improvise.info","status":"available","attractiveness":76,"demand":4,"length":9,"created":"","expires":"","registrar":null,"sectors":"Entertainment"},{"domain":"addable.info","status":"available","attractiveness":76,"demand":2,"length":7,"created":"","expires":"","registrar":null,"sectors":"Engineering,Mathematics,Science"},{"domain":"diamond.info","status":"resell","attractiveness":76,"demand":32,"length":7,"created":"2002-07-13T19:23:26.000Z","expires":"2026-07-13T19:23:26.000Z","registrar":"NameCheap, Inc.","sectors":"Fashion"},{"domain":"resultant.info","status":"available","attractiveness":76,"demand":2,"length":9,"created":"","expires":"","registrar":null,"sectors":"Healthcare,Insurance,Transportation"},{"domain":"eighteen.info","status":"resell","attractiveness":76,"demand":7,"length":8,"created":"2024-12-08T17:00:02.000Z","expires":"2025-12-08T17:00:02.000Z","registrar":"Sav.com, LLC - 38","sectors":"Mathematics"},{"domain":"auxiliary.info","status":"available","attractiveness":76,"demand":7,"length":9,"created":"","expires":"","registrar":null,"sectors":"Healthcare,Manufacturing,Technology"},{"domain":"threed.info","status":"available","attractiveness":76,"demand":7,"length":7,"created":"","expires":"","registrar":null,"sectors":"Technology"},{"domain":"obscene.info","status":"available","attractiveness":76,"demand":5,"length":7,"created":"","expires":"","registrar":null,"sectors":"Entertainment,Media"},{"domain":"energizing.info","status":"available","attractiveness":76,"demand":3,"length":10,"created":"","expires":"","registrar":null,"sectors":"Food and Beverage,Health and Fitness,Travel"},{"domain":"adaptable.info","status":"resell","attractiveness":76,"demand":9,"length":9,"created":"2024-08-12T17:00:00.000Z","expires":"2026-08-12T17:00:00.000Z","registrar":"Sav.com, LLC - 8","sectors":"Business,Education,Technology"},{"domain":"thousandth.info","status":"available","attractiveness":76,"demand":1,"length":10,"created":"","expires":"","registrar":null,"sectors":"Mathematics"},{"domain":"nineteenth.info","status":"available","attractiveness":76,"demand":3,"length":10,"created":"","expires":"","registrar":null,"sectors":"Mathematics"},{"domain":"adhesive.info","status":"available","attractiveness":76,"demand":7,"length":8,"created":"","expires":"","registrar":null,"sectors":"Construction,Manufacturing,Technology"},{"domain":"adipose.info","status":"available","attractiveness":76,"demand":2,"length":7,"created":"","expires":"","registrar":null,"sectors":"Healthcare,Science"},{"domain":"fourteenth.info","status":"expiring","attractiveness":76,"demand":2,"length":10,"created":"2023-09-14T17:15:50.000Z","expires":"2025-09-14T17:15:50.000Z","registrar":"GoDaddy.com, LLC","sectors":"Mathematics"},{"domain":"ague.info","status":"available","attractiveness":76,"demand":2,"length":4,"created":"","expires":"","registrar":null,"sectors":"Geography,Medicine,Science"},{"domain":"acuate.info","status":"available","attractiveness":74,"demand":2,"length":6,"created":"","expires":"","registrar":null,"sectors":"Engineering,Medicine,Science"},{"domain":"adrenergic.info","status":"available","attractiveness":74,"demand":1,"length":10,"created":"","expires":"","registrar":null,"sectors":"Education,Healthcare,Science"},{"domain":"adenoid.info","status":"available","attractiveness":74,"demand":1,"length":7,"created":"","expires":"","registrar":null,"sectors":"Health and Fitness,Medicine,Science"},{"domain":"sensation.info","status":"expired","attractiveness":74,"demand":7,"length":9,"created":"2024-07-03T15:16:02.000Z","expires":"2025-07-03T15:16:02.000Z","registrar":"Sav.com, LLC - 10","sectors":"Entertainment,Media,Sports"},{"domain":"admirable.info","status":"available","attractiveness":74,"demand":5,"length":9,"created":"","expires":"","registrar":null,"sectors":"Business,Education,Healthcare"},{"domain":"adapted.info","status":"resell","attractiveness":74,"demand":6,"length":7,"created":"2024-12-30T15:03:00.000Z","expires":"2025-12-30T15:03:00.000Z","registrar":"Alibaba Cloud Computing Ltd. d/b/a HiChina (www.net.cn)","sectors":"Healthcare,Manufacturing,Technology"},{"domain":"supra.info","status":"resell","attractiveness":74,"demand":25,"length":5,"created":"2016-02-05T10:07:49.000Z","expires":"2026-02-05T10:07:49.000Z","registrar":"Dynadot Inc","sectors":"Medicine,Science"},{"domain":"accepting.info","status":"resell","attractiveness":74,"demand":3,"length":9,"created":"2024-10-08T21:44:05.000Z","expires":"2025-10-08T21:44:05.000Z","registrar":"NameCheap, Inc.","sectors":"Education,Healthcare"},{"domain":"manageable.info","status":"available","attractiveness":74,"demand":4,"length":10,"created":"","expires":"","registrar":null,"sectors":"Business,Education,Technology"},{"domain":"realizable.info","status":"available","attractiveness":74,"demand":1,"length":10,"created":"","expires":"","registrar":null,"sectors":"Business,Education,Technology"},{"domain":"cleared.info","status":"expired","attractiveness":74,"demand":7,"length":7,"created":"2024-06-24T17:51:33.000Z","expires":"2025-06-24T17:51:33.000Z","registrar":"GoDaddy.com, LLC","sectors":"Healthcare,Law,Transportation"},{"domain":"skilful.info","status":"available","attractiveness":74,"demand":3,"length":7,"created":"","expires":"","registrar":null,"sectors":"Education,Health and Fitness,Sports"},{"domain":"improvize.info","status":"available","attractiveness":72,"demand":1,"length":9,"created":"","expires":"","registrar":null,"sectors":"Entertainment"},{"domain":"adiabatic.info","status":"available","attractiveness":72,"demand":3,"length":9,"created":"","expires":"","registrar":null,"sectors":"Engineering,Science"},{"domain":"existent.info","status":"available","attractiveness":72,"demand":3,"length":8,"created":"","expires":"","registrar":null,"sectors":"Mathematics,Science"},{"domain":"aching.info","status":"available","attractiveness":72,"demand":4,"length":6,"created":"","expires":"","registrar":null,"sectors":"Healthcare"},{"domain":"adjectival.info","status":"available","attractiveness":72,"demand":1,"length":10,"created":"","expires":"","registrar":null,"sectors":"Education"},{"domain":"sixtieth.info","status":"available","attractiveness":72,"demand":1,"length":8,"created":"","expires":"","registrar":null,"sectors":"Mathematics"},{"domain":"liv.info","status":"resell","attractiveness":72,"demand":28,"length":3,"created":"2004-02-20T09:56:38.000Z","expires":"2026-02-20T09:56:38.000Z","registrar":"Dynadot Inc","sectors":"Mathematics"},{"domain":"seventieth.info","status":"available","attractiveness":72,"demand":1,"length":10,"created":"","expires":"","registrar":null,"sectors":"Mathematics"},{"domain":"trey.info","status":"resell","attractiveness":72,"demand":13,"length":4,"created":"2022-07-18T16:26:55.000Z","expires":"2026-07-18T16:26:55.000Z","registrar":"NameCheap, Inc.","sectors":"Sports"},{"domain":"adonic.info","status":"available","attractiveness":72,"demand":2,"length":6,"created":"","expires":"","registrar":null,"sectors":"Arts,Education,Entertainment"},{"domain":"adaptative.info","status":"available","attractiveness":72,"demand":1,"length":10,"created":"","expires":"","registrar":null,"sectors":"Business,Education,Technology"},{"domain":"champion.info","status":"resell","attractiveness":72,"demand":28,"length":8,"created":"2001-07-31T20:42:58.000Z","expires":"2026-07-31T20:42:58.000Z","registrar":"Dynadot Inc","sectors":"Entertainment,Health and Fitness,Sports"},{"domain":"ninetieth.info","status":"available","attractiveness":72,"demand":1,"length":9,"created":"","expires":"","registrar":null,"sectors":"Mathematics"},{"domain":"absolutist.info","status":"available","attractiveness":72,"demand":1,"length":10,"created":"","expires":"","registrar":null,"sectors":"Humanities,Law,Politics"},{"domain":"accusative.info","status":"available","attractiveness":72,"demand":0,"length":10,"created":"","expires":"","registrar":null,"sectors":"Humanities,Law"},{"domain":"eightieth.info","status":"available","attractiveness":72,"demand":1,"length":9,"created":"","expires":"","registrar":null,"sectors":"Mathematics"},{"domain":"accustomed.info","status":"available","attractiveness":72,"demand":1,"length":10,"created":"","expires":"","registrar":null,"sectors":"Business,Education,Humanities"},{"domain":"abloom.info","status":"expiring","attractiveness":72,"demand":5,"length":6,"created":"2021-09-12T14:27:41.000Z","expires":"2025-09-12T14:27:41.000Z","registrar":"GMO Internet Group, Inc. d/b/a Onamae.com","sectors":"Agriculture"},{"domain":"ablaze.info","status":"available","attractiveness":72,"demand":6,"length":6,"created":"","expires":"","registrar":null,"sectors":"Entertainment"},{"domain":"engrossed.info","status":"available","attractiveness":72,"demand":1,"length":9,"created":"","expires":"","registrar":null,"sectors":"Entertainment,Media,Technology"},{"domain":"adjunctive.info","status":"available","attractiveness":72,"demand":1,"length":10,"created":"","expires":"","registrar":null,"sectors":"Healthcare,Manufacturing,Technology"},{"domain":"abradant.info","status":"available","attractiveness":70,"demand":1,"length":8,"created":"","expires":"","registrar":null,"sectors":"Construction,Manufacturing"},{"domain":"adored.info","status":"resell","attractiveness":70,"demand":6,"length":6,"created":"2024-08-06T17:00:02.000Z","expires":"2026-08-06T17:00:02.000Z","registrar":"Sav.com, LLC - 15","sectors":"Entertainment,Fashion,Retail"},{"domain":"abulic.info","status":"available","attractiveness":70,"demand":1,"length":6,"created":"","expires":"","registrar":null,"sectors":"Medicine"},{"domain":"consequent.info","status":"available","attractiveness":70,"demand":3,"length":10,"created":"","expires":"","registrar":null,"sectors":"Business,Education,General,Technology"},{"domain":"acuminate.info","status":"available","attractiveness":70,"demand":1,"length":9,"created":"","expires":"","registrar":null,"sectors":"Engineering,Medicine,Science"},{"domain":"gymnastic.info","status":"expiring","attractiveness":70,"demand":3,"length":9,"created":"2001-09-16T18:15:21.000Z","expires":"2025-09-16T18:15:21.000Z","registrar":"InterNetX GmbH","sectors":"Entertainment,Sports"},{"domain":"practiced.info","status":"available","attractiveness":70,"demand":3,"length":9,"created":"","expires":"","registrar":null,"sectors":"Education,Health and Fitness,Sports"},{"domain":"accumbent.info","status":"available","attractiveness":70,"demand":1,"length":9,"created":"","expires":"","registrar":null,"sectors":"Healthcare,Medicine,Science"},{"domain":"admired.info","status":"available","attractiveness":70,"demand":5,"length":7,"created":"","expires":"","registrar":null,"sectors":"Business,Education,Healthcare"},{"domain":"recumbent.info","status":"available","attractiveness":70,"demand":2,"length":9,"created":"","expires":"","registrar":null,"sectors":"Healthcare,Medicine,Science"},{"domain":"absorbing.info","status":"available","attractiveness":70,"demand":3,"length":9,"created":"","expires":"","registrar":null,"sectors":"Entertainment,Media,Technology"},{"domain":"skillful.info","status":"resell","attractiveness":70,"demand":9,"length":8,"created":"2025-05-20T06:02:14.000Z","expires":"2026-05-20T06:02:14.000Z","registrar":"Mesh Digital Limited","sectors":"Education,Health and Fitness,Sports"},{"domain":"offhand.info","status":"available","attractiveness":70,"demand":2,"length":7,"created":"","expires":"","registrar":null,"sectors":"Entertainment"},{"domain":"unity.info","status":"expiring","attractiveness":70,"demand":38,"length":5,"created":"2001-09-21T05:30:54.000Z","expires":"2025-09-21T05:30:54.000Z","registrar":"Porkbun LLC","sectors":"Mathematics"},{"domain":"stillborn.info","status":"available","attractiveness":70,"demand":2,"length":9,"created":"","expires":"","registrar":null,"sectors":"Medicine,Science"},{"domain":"adjusted.info","status":"available","attractiveness":70,"demand":5,"length":8,"created":"","expires":"","registrar":null,"sectors":"Manufacturing,Retail,Technology"},{"domain":"miserable.info","status":"available","attractiveness":70,"demand":4,"length":9,"created":"","expires":"","registrar":null,"sectors":"Humanities"},{"domain":"thirtieth.info","status":"available","attractiveness":68,"demand":1,"length":9,"created":"","expires":"","registrar":null,"sectors":"Mathematics"},{"domain":"ennead.info","status":"available","attractiveness":68,"demand":5,"length":6,"created":"","expires":"","registrar":null,"sectors":"Mathematics"},{"domain":"licensed.info","status":"resell","attractiveness":68,"demand":5,"length":8,"created":"2025-01-31T15:15:08.000Z","expires":"2026-01-31T15:15:08.000Z","registrar":"Sav.com, LLC - 1","sectors":"Business,Healthcare,Insurance"},{"domain":"stygian.info","status":"available","attractiveness":68,"demand":5,"length":7,"created":"","expires":"","registrar":null,"sectors":"Humanities"},{"domain":"aberdonian.info","status":"available","attractiveness":68,"demand":1,"length":10,"created":"","expires":"","registrar":null,"sectors":"Geography"},{"domain":"achaean.info","status":"available","attractiveness":68,"demand":2,"length":7,"created":"","expires":"","registrar":null,"sectors":"Humanities"},{"domain":"disciple.info","status":"resell","attractiveness":68,"demand":14,"length":8,"created":"2022-10-04T17:39:57.000Z","expires":"2025-10-04T17:39:57.000Z","registrar":"NameCheap, Inc.","sectors":"Education,Religion"},{"domain":"accredited.info","status":"resell","attractiveness":68,"demand":9,"length":10,"created":"2024-11-11T20:46:20.000Z","expires":"2025-11-11T20:46:20.000Z","registrar":"GoDaddy.com, LLC","sectors":"Business,Education,Healthcare"},{"domain":"abkhas.info","status":"available","attractiveness":68,"demand":0,"length":6,"created":"","expires":"","registrar":null,"sectors":"Geography"},{"domain":"aroused.info","status":"available","attractiveness":68,"demand":3,"length":7,"created":"","expires":"","registrar":null,"sectors":"Entertainment,Health and Fitness"},{"domain":"overseas.info","status":"resell","attractiveness":68,"demand":12,"length":8,"created":"2002-07-13T19:27:08.000Z","expires":"2026-07-13T19:27:08.000Z","registrar":"Dynadot Inc","sectors":"Hospitality,Travel"},{"domain":"fortieth.info","status":"available","attractiveness":68,"demand":1,"length":8,"created":"","expires":"","registrar":null,"sectors":"Mathematics"},{"domain":"ane.info","status":"resell","attractiveness":68,"demand":12,"length":3,"created":"2006-12-22T09:35:51.000Z","expires":"2025-12-22T09:35:51.000Z","registrar":"Sea Wasp, LLC","sectors":"Mathematics"},{"domain":"ablative.info","status":"available","attractiveness":68,"demand":3,"length":8,"created":"","expires":"","registrar":null,"sectors":"Science"},{"domain":"licenced.info","status":"available","attractiveness":68,"demand":2,"length":8,"created":"","expires":"","registrar":null,"sectors":"Business,Healthcare,Insurance"},{"domain":"octonary.info","status":"available","attractiveness":68,"demand":1,"length":8,"created":"","expires":"","registrar":null,"sectors":"Mathematics"},{"domain":"foursome.info","status":"available","attractiveness":68,"demand":4,"length":8,"created":"","expires":"","registrar":null,"sectors":"Sports"},{"domain":"aculeate.info","status":"available","attractiveness":68,"demand":1,"length":8,"created":"","expires":"","registrar":null,"sectors":"Engineering,Medicine,Science"},{"domain":"abducent.info","status":"available","attractiveness":68,"demand":0,"length":8,"created":"","expires":"","registrar":null,"sectors":"Medicine"},{"domain":"vindicated.info","status":"available","attractiveness":68,"demand":2,"length":10,"created":"","expires":"","registrar":null,"sectors":"Humanities,Law,Politics"},{"domain":"abnaki.info","status":"available","attractiveness":68,"demand":1,"length":6,"created":"","expires":"","registrar":null,"sectors":"Geography"},{"domain":"acerate.info","status":"available","attractiveness":68,"demand":1,"length":7,"created":"","expires":"","registrar":null,"sectors":"Science"},{"domain":"fiftieth.info","status":"available","attractiveness":68,"demand":1,"length":8,"created":"","expires":"","registrar":null,"sectors":"Mathematics"},{"domain":"threesome.info","status":"resell","attractiveness":68,"demand":5,"length":9,"created":"2024-11-29T22:11:22.000Z","expires":"2025-11-29T22:11:22.000Z","registrar":"GoDaddy.com, LLC","sectors":"Entertainment"},{"domain":"sevener.info","status":"available","attractiveness":68,"demand":1,"length":7,"created":"","expires":"","registrar":null,"sectors":"Mathematics"},{"domain":"achaian.info","status":"available","attractiveness":68,"demand":2,"length":7,"created":"","expires":"","registrar":null,"sectors":"Humanities"},{"domain":"activating.info","status":"available","attractiveness":68,"demand":3,"length":10,"created":"","expires":"","registrar":null,"sectors":"Healthcare,Manufacturing,Technology"},{"domain":"scurvy.info","status":"available","attractiveness":68,"demand":3,"length":6,"created":"","expires":"","registrar":null,"sectors":"Humanities"},{"domain":"deuce.info","status":"resell","attractiveness":66,"demand":8,"length":5,"created":"2024-12-30T11:36:46.000Z","expires":"2025-12-30T11:36:46.000Z","registrar":"Alibaba Cloud Computing Ltd. d/b/a HiChina (www.net.cn)","sectors":"Sports"},{"domain":"modish.info","status":"resell","attractiveness":66,"demand":5,"length":6,"created":"2024-12-30T11:45:55.000Z","expires":"2025-12-30T11:45:55.000Z","registrar":"Alibaba Cloud Computing Ltd. d/b/a HiChina (www.net.cn)","sectors":"Fashion"},{"domain":"xxvi.info","status":"available","attractiveness":66,"demand":3,"length":4,"created":"","expires":"","registrar":null,"sectors":"Mathematics"},{"domain":"performing.info","status":"resell","attractiveness":66,"demand":6,"length":10,"created":"2024-12-30T15:04:53.000Z","expires":"2025-12-30T15:04:53.000Z","registrar":"Alibaba Cloud Computing Ltd. d/b/a HiChina (www.net.cn)","sectors":"Entertainment"},{"domain":"xii.info","status":"resell","attractiveness":66,"demand":10,"length":3,"created":"2025-05-26T15:16:03.000Z","expires":"2026-05-26T15:16:03.000Z","registrar":"Sav.com, LLC - 49","sectors":"Mathematics"},{"domain":"according.info","status":"available","attractiveness":66,"demand":3,"length":9,"created":"","expires":"","registrar":null,"sectors":"Business,Education,Technology"},{"domain":"century.info","status":"sold","attractiveness":66,"demand":17,"length":7,"created":"2001-08-16T14:59:50.000Z","expires":"2026-08-16T14:59:50.000Z","registrar":"GoDaddy.com, LLC","sectors":"Education"},{"domain":"abstinent.info","status":"available","attractiveness":66,"demand":1,"length":9,"created":"","expires":"","registrar":null,"sectors":"Health and Fitness,Religion"},{"domain":"latest.info","status":"resell","attractiveness":66,"demand":18,"length":6,"created":"2004-10-02T09:36:29.000Z","expires":"2025-10-02T09:36:29.000Z","registrar":"Moniker Online Services LLC","sectors":"Technology"},{"domain":"tenner.info","status":"available","attractiveness":66,"demand":4,"length":6,"created":"","expires":"","registrar":null,"sectors":"Finance"},{"domain":"sextet.info","status":"available","attractiveness":66,"demand":2,"length":6,"created":"","expires":"","registrar":null,"sectors":"Entertainment"},{"domain":"xviii.info","status":"available","attractiveness":66,"demand":4,"length":5,"created":"","expires":"","registrar":null,"sectors":"Mathematics"},{"domain":"acrobatic.info","status":"resell","attractiveness":66,"demand":4,"length":9,"created":"2024-12-30T16:24:56.000Z","expires":"2025-12-30T16:24:56.000Z","registrar":"Alibaba Cloud Computing Ltd. d/b/a HiChina (www.net.cn)","sectors":"Entertainment,Sports"},{"domain":"acervate.info","status":"available","attractiveness":66,"demand":1,"length":8,"created":"","expires":"","registrar":null,"sectors":"Science"},{"domain":"thirty.info","status":"sold","attractiveness":66,"demand":7,"length":6,"created":"2025-08-21T02:01:34.000Z","expires":"2026-08-21T02:01:34.000Z","registrar":"GoDaddy.com, LLC","sectors":"Mathematics"},{"domain":"accessary.info","status":"available","attractiveness":66,"demand":1,"length":9,"created":"","expires":"","registrar":null,"sectors":"Business,Law,Technology"},{"domain":"acappella.info","status":"available","attractiveness":66,"demand":6,"length":10,"created":"","expires":"","registrar":null,"sectors":"Entertainment"},{"domain":"ninety.info","status":"resell","attractiveness":66,"demand":11,"length":6,"created":"2025-01-25T15:15:14.000Z","expires":"2026-01-25T15:15:14.000Z","registrar":"Sav.com, LLC - 45","sectors":"Mathematics"},{"domain":"xvii.info","status":"resell","attractiveness":66,"demand":5,"length":4,"created":"2024-12-30T15:57:52.000Z","expires":"2025-12-30T15:57:52.000Z","registrar":"Alibaba Cloud Computing Ltd. d/b/a HiChina (www.net.cn)","sectors":"Mathematics"},{"domain":"xvi.info","status":"resell","attractiveness":66,"demand":4,"length":3,"created":"2024-07-28T17:00:01.000Z","expires":"2026-07-28T17:00:01.000Z","registrar":"Sav.com, LLC - 2","sectors":"Mathematics"},{"domain":"fifty.info","status":"resell","attractiveness":66,"demand":13,"length":5,"created":"2025-01-15T15:15:12.000Z","expires":"2026-01-15T15:15:12.000Z","registrar":"Sav.com, LLC - 36","sectors":"Mathematics"},{"domain":"xxii.info","status":"resell","attractiveness":66,"demand":6,"length":4,"created":"2014-12-08T18:23:15.000Z","expires":"2025-12-08T18:23:15.000Z","registrar":"GoDaddy.com, LLC","sectors":"Mathematics"},{"domain":"five.info","status":"resell","attractiveness":66,"demand":26,"length":4,"created":"2005-12-02T09:43:31.000Z","expires":"2025-12-02T09:43:31.000Z","registrar":"Dynadot Inc","sectors":"Mathematics"},{"domain":"clv.info","status":"resell","attractiveness":66,"demand":10,"length":3,"created":"2024-10-21T17:00:01.000Z","expires":"2025-10-21T17:00:01.000Z","registrar":"Sav.com, LLC - 12","sectors":"Mathematics"},{"domain":"teenager.info","status":"resell","attractiveness":66,"demand":4,"length":8,"created":"2002-07-13T19:25:21.000Z","expires":"2026-07-13T19:25:21.000Z","registrar":"Spaceship, Inc.","sectors":"Education,Entertainment,Healthcare"},{"domain":"scatty.info","status":"available","attractiveness":64,"demand":1,"length":6,"created":"","expires":"","registrar":null,"sectors":"Arts,Entertainment,Media"},{"domain":"rising.info","status":"resell","attractiveness":64,"demand":18,"length":6,"created":"2021-08-01T14:31:02.000Z","expires":"2026-08-01T14:31:02.000Z","registrar":"Squarespace Domains II LLC","sectors":"Construction,Manufacturing,Real Estate"},{"domain":"deviant.info","status":"resell","attractiveness":64,"demand":12,"length":7,"created":"2005-01-22T09:39:09.000Z","expires":"2026-01-22T09:39:09.000Z","registrar":"Dynadot Inc","sectors":"Medicine,Science"},{"domain":"astringent.info","status":"available","attractiveness":64,"demand":1,"length":10,"created":"","expires":"","registrar":null,"sectors":"Healthcare,Pharmaceuticals"},{"domain":"adagio.info","status":"expired","attractiveness":64,"demand":14,"length":6,"created":"2024-06-22T17:00:02.000Z","expires":"2025-06-22T17:00:02.000Z","registrar":"Sav.com, LLC - 14","sectors":"Entertainment"},{"domain":"acentric.info","status":"available","attractiveness":64,"demand":2,"length":8,"created":"","expires":"","registrar":null,"sectors":"Science"},{"domain":"nondrinker.info","status":"available","attractiveness":64,"demand":1,"length":10,"created":"","expires":"","registrar":null,"sectors":"Health and Fitness,Religion"},{"domain":"absolved.info","status":"available","attractiveness":64,"demand":1,"length":8,"created":"","expires":"","registrar":null,"sectors":"Humanities,Law,Religion"},{"domain":"aflame.info","status":"available","attractiveness":64,"demand":3,"length":6,"created":"","expires":"","registrar":null,"sectors":"Entertainment"},{"domain":"ccc.info","status":"resell","attractiveness":64,"demand":38,"length":3,"created":"2018-10-04T10:16:34.000Z","expires":"2025-10-04T10:16:34.000Z","registrar":"1API GmbH","sectors":"Mathematics"},{"domain":"playacting.info","status":"available","attractiveness":62,"demand":1,"length":10,"created":"","expires":"","registrar":null,"sectors":"Entertainment"},{"domain":"acidic.info","status":"available","attractiveness":62,"demand":5,"length":6,"created":"","expires":"","registrar":null,"sectors":"Food and Beverage,Science"},{"domain":"sixteenth.info","status":"resell","attractiveness":62,"demand":1,"length":9,"created":"2024-10-02T00:01:26.000Z","expires":"2025-10-02T00:01:26.000Z","registrar":"NameCheap, Inc.","sectors":"Mathematics"},{"domain":"adjuvant.info","status":"resell","attractiveness":62,"demand":5,"length":8,"created":"2024-12-30T15:52:42.000Z","expires":"2025-12-30T15:52:42.000Z","registrar":"Alibaba Cloud Computing Ltd. d/b/a HiChina (www.net.cn)","sectors":"Healthcare,Manufacturing,Technology"},{"domain":"adoptive.info","status":"available","attractiveness":62,"demand":1,"length":8,"created":"","expires":"","registrar":null,"sectors":"Education,Healthcare"},{"domain":"accrued.info","status":"available","attractiveness":62,"demand":2,"length":7,"created":"","expires":"","registrar":null,"sectors":"Banking,Finance,Insurance"},{"domain":"twodozen.info","status":"available","attractiveness":62,"demand":1,"length":9,"created":"","expires":"","registrar":null,"sectors":"Mathematics"},{"domain":"activation.info","status":"resell","attractiveness":62,"demand":16,"length":10,"created":"2017-02-19T10:07:41.000Z","expires":"2026-02-19T10:07:41.000Z","registrar":"Dot Holding Inc.","sectors":"Healthcare,Manufacturing,Technology"},{"domain":"admissible.info","status":"available","attractiveness":62,"demand":1,"length":10,"created":"","expires":"","registrar":null,"sectors":"Education,Healthcare,Law"},{"domain":"eighteenth.info","status":"available","attractiveness":62,"demand":1,"length":10,"created":"","expires":"","registrar":null,"sectors":"Mathematics"},{"domain":"orso.info","status":"resell","attractiveness":62,"demand":9,"length":5,"created":"2024-12-06T17:00:02.000Z","expires":"2025-12-06T17:00:02.000Z","registrar":"Sav.com, LLC - 10","sectors":"Business,Media,Technology"},{"domain":"roughly.info","status":"available","attractiveness":62,"demand":3,"length":7,"created":"","expires":"","registrar":null,"sectors":"Business,Media,Technology"},{"domain":"cumulative.info","status":"available","attractiveness":62,"demand":2,"length":10,"created":"","expires":"","registrar":null,"sectors":"Banking,Finance,Insurance"},{"domain":"activistic.info","status":"available","attractiveness":62,"demand":1,"length":10,"created":"","expires":"","registrar":null,"sectors":"Humanities,Politics"},{"domain":"longdozen.info","status":"available","attractiveness":62,"demand":1,"length":10,"created":"","expires":"","registrar":null,"sectors":"Mathematics"},{"domain":"aufait.info","status":"available","attractiveness":62,"demand":3,"length":7,"created":"","expires":"","registrar":null,"sectors":"Fashion,Media"},{"domain":"chiliad.info","status":"available","attractiveness":62,"demand":2,"length":7,"created":"","expires":"","registrar":null,"sectors":"Mathematics"},{"domain":"troika.info","status":"resell","attractiveness":62,"demand":8,"length":6,"created":"2025-01-17T15:15:36.000Z","expires":"2026-01-17T15:15:36.000Z","registrar":"Sav.com, LLC - 45","sectors":"Politics"},{"domain":"exculpated.info","status":"available","attractiveness":62,"demand":1,"length":10,"created":"","expires":"","registrar":null,"sectors":"Humanities,Law,Politics"},{"domain":"wrapped.info","status":"resell","attractiveness":62,"demand":13,"length":7,"created":"2025-04-13T15:15:42.000Z","expires":"2026-04-13T15:15:42.000Z","registrar":"Sav.com, LLC - 44","sectors":"Fashion,Hospitality,Retail"},{"domain":"fortyfour.info","status":"resell","attractiveness":62,"demand":6,"length":10,"created":"2024-12-30T15:18:49.000Z","expires":"2025-12-30T15:18:49.000Z","registrar":"Alibaba Cloud Computing Ltd. d/b/a HiChina (www.net.cn)","sectors":"Mathematics"},{"domain":"accusing.info","status":"available","attractiveness":62,"demand":1,"length":8,"created":"","expires":"","registrar":null,"sectors":"Law"},{"domain":"ensuant.info","status":"available","attractiveness":62,"demand":1,"length":7,"created":"","expires":"","registrar":null,"sectors":"Healthcare,Insurance,Transportation"},{"domain":"pungent.info","status":"available","attractiveness":62,"demand":1,"length":7,"created":"","expires":"","registrar":null,"sectors":"Food and Beverage"},{"domain":"eleventh.info","status":"resell","attractiveness":62,"demand":5,"length":8,"created":"2025-03-09T03:24:08.000Z","expires":"2026-03-09T03:24:08.000Z","registrar":"Spaceship, Inc.","sectors":"Mathematics"},{"domain":"nail.info","status":"resell","attractiveness":62,"demand":16,"length":4,"created":"2003-11-26T08:08:15.000Z","expires":"2025-11-26T08:08:15.000Z","registrar":"InterNetX GmbH","sectors":"Construction,Fashion,General,Retail"},{"domain":"abo.info","status":"expired","attractiveness":62,"demand":15,"length":3,"created":"2017-07-05T10:05:10.000Z","expires":"2025-07-05T10:05:10.000Z","registrar":"1API GmbH","sectors":"Science"},{"domain":"quartet.info","status":"available","attractiveness":62,"demand":7,"length":7,"created":"","expires":"","registrar":null,"sectors":"Arts,Entertainment"},{"domain":"adnexal.info","status":"available","attractiveness":60,"demand":1,"length":7,"created":"","expires":"","registrar":null,"sectors":"Agriculture,Manufacturing,Retail"},{"domain":"xcl.info","status":"available","attractiveness":60,"demand":5,"length":3,"created":"","expires":"","registrar":null,"sectors":"Mathematics"},{"domain":"cxxv.info","status":"available","attractiveness":60,"demand":1,"length":4,"created":"","expires":"","registrar":null,"sectors":"Mathematics"},{"domain":"clx.info","status":"resell","attractiveness":60,"demand":8,"length":3,"created":"2001-10-27T02:52:18.000Z","expires":"2025-10-27T02:52:18.000Z","registrar":"Realtime Register B.V.","sectors":"Mathematics"},{"domain":"acceptive.info","status":"available","attractiveness":60,"demand":1,"length":9,"created":"","expires":"","registrar":null,"sectors":"Education,Healthcare"},{"domain":"cxl.info","status":"available","attractiveness":60,"demand":7,"length":3,"created":"","expires":"","registrar":null,"sectors":"Mathematics"},{"domain":"cxxxv.info","status":"available","attractiveness":60,"demand":1,"length":5,"created":"","expires":"","registrar":null,"sectors":"Mathematics"},{"domain":"annexal.info","status":"available","attractiveness":60,"demand":1,"length":7,"created":"","expires":"","registrar":null,"sectors":"Agriculture,Manufacturing,Retail"},{"domain":"idolised.info","status":"available","attractiveness":60,"demand":1,"length":8,"created":"","expires":"","registrar":null,"sectors":"Entertainment,Fashion,Retail"},{"domain":"abashed.info","status":"available","attractiveness":60,"demand":1,"length":7,"created":"","expires":"","registrar":null,"sectors":"Humanities"},{"domain":"cautionary.info","status":"available","attractiveness":60,"demand":1,"length":10,"created":"","expires":"","registrar":null,"sectors":"Business,Education,Healthcare"},{"domain":"cxv.info","status":"resell","attractiveness":60,"demand":4,"length":3,"created":"2024-08-06T17:00:59.000Z","expires":"2026-08-06T17:00:59.000Z","registrar":"Sav.com, LLC","sectors":"Mathematics"},{"domain":"clxv.info","status":"available","attractiveness":60,"demand":1,"length":4,"created":"","expires":"","registrar":null,"sectors":"Mathematics"},{"domain":"abstemious.info","status":"expiring","attractiveness":60,"demand":0,"length":10,"created":"2022-09-08T15:29:34.000Z","expires":"2025-09-08T15:29:34.000Z","registrar":"Tucows Domains Inc.","sectors":"Food and Beverage,Health and Fitness,Hospitality"},{"domain":"tertiary.info","status":"available","attractiveness":60,"demand":4,"length":8,"created":"","expires":"","registrar":null,"sectors":"Education"},{"domain":"adnate.info","status":"available","attractiveness":60,"demand":1,"length":6,"created":"","expires":"","registrar":null,"sectors":"Agriculture,Manufacturing,Retail"},{"domain":"abstainer.info","status":"available","attractiveness":60,"demand":0,"length":9,"created":"","expires":"","registrar":null,"sectors":"Health and Fitness,Religion"},{"domain":"clxxx.info","status":"available","attractiveness":60,"demand":1,"length":5,"created":"","expires":"","registrar":null,"sectors":"Mathematics"},{"domain":"cxxx.info","status":"available","attractiveness":60,"demand":3,"length":4,"created":"","expires":"","registrar":null,"sectors":"Mathematics"},{"domain":"clxx.info","status":"available","attractiveness":60,"demand":2,"length":4,"created":"","expires":"","registrar":null,"sectors":"Mathematics"},{"domain":"paunchy.info","status":"available","attractiveness":60,"demand":0,"length":7,"created":"","expires":"","registrar":null,"sectors":"Health and Fitness,Medicine"},{"domain":"clxxv.info","status":"available","attractiveness":60,"demand":1,"length":5,"created":"","expires":"","registrar":null,"sectors":"Mathematics"},{"domain":"tercet.info","status":"available","attractiveness":59,"demand":2,"length":6,"created":"","expires":"","registrar":null,"sectors":"Arts,Entertainment,Media"},{"domain":"closeto.info","status":"available","attractiveness":58,"demand":3,"length":8,"created":"","expires":"","registrar":null,"sectors":"Business,Media,Technology"},{"domain":"acyclic.info","status":"available","attractiveness":58,"demand":4,"length":7,"created":"","expires":"","registrar":null,"sectors":"Engineering,Mathematics,Science"},{"domain":"octad.info","status":"available","attractiveness":58,"demand":5,"length":5,"created":"","expires":"","registrar":null,"sectors":"Mathematics"},{"domain":"abused.info","status":"available","attractiveness":58,"demand":5,"length":6,"created":"","expires":"","registrar":null,"sectors":"Healthcare,Law"},{"domain":"sixer.info","status":"available","attractiveness":58,"demand":5,"length":5,"created":"","expires":"","registrar":null,"sectors":"Sports"},{"domain":"justabout.info","status":"available","attractiveness":58,"demand":3,"length":10,"created":"","expires":"","registrar":null,"sectors":"Business,Media,Technology"},{"domain":"fourth.info","status":"resell","attractiveness":58,"demand":13,"length":6,"created":"2025-02-26T15:15:34.000Z","expires":"2026-02-26T15:15:34.000Z","registrar":"Sav.com, LLC - 45","sectors":"Mathematics"},{"domain":"cypher.info","status":"sold","attractiveness":58,"demand":28,"length":6,"created":"2001-09-15T11:52:59.000Z","expires":"2026-09-15T11:52:59.000Z","registrar":"Tucows Domains Inc.","sectors":"Mathematics"},{"domain":"fifth.info","status":"expired","attractiveness":58,"demand":12,"length":5,"created":"2024-06-11T17:00:01.000Z","expires":"2025-06-11T17:00:01.000Z","registrar":"Sav.com, LLC - 45","sectors":"Mathematics"},{"domain":"accoutred.info","status":"available","attractiveness":58,"demand":1,"length":9,"created":"","expires":"","registrar":null,"sectors":"Fashion,Manufacturing,Retail"},{"domain":"pentad.info","status":"available","attractiveness":58,"demand":3,"length":6,"created":"","expires":"","registrar":null,"sectors":"Mathematics"},{"domain":"quintet.info","status":"available","attractiveness":58,"demand":8,"length":7,"created":"","expires":"","registrar":null,"sectors":"Arts,Entertainment"},{"domain":"accretive.info","status":"available","attractiveness":58,"demand":6,"length":9,"created":"","expires":"","registrar":null,"sectors":"Banking,Finance,Insurance"},{"domain":"addressed.info","status":"available","attractiveness":58,"demand":3,"length":9,"created":"","expires":"","registrar":null,"sectors":"Business,Technology,Telecommunications"},{"domain":"heptad.info","status":"available","attractiveness":58,"demand":2,"length":6,"created":"","expires":"","registrar":null,"sectors":"Mathematics"},{"domain":"actuarial.info","status":"expiring","attractiveness":58,"demand":8,"length":9,"created":"2001-09-17T07:34:35.000Z","expires":"2025-09-17T07:34:35.000Z","registrar":"Tucows Domains Inc.","sectors":"Finance,Insurance,Mathematics"},{"domain":"lxxx.info","status":"available","attractiveness":58,"demand":2,"length":4,"created":"","expires":"","registrar":null,"sectors":"Mathematics"},{"domain":"twelfth.info","status":"available","attractiveness":58,"demand":2,"length":7,"created":"","expires":"","registrar":null,"sectors":"Mathematics"},{"domain":"abuzz.info","status":"available","attractiveness":58,"demand":5,"length":5,"created":"","expires":"","registrar":null,"sectors":"Entertainment,Media,Technology"},{"domain":"sextuplet.info","status":"available","attractiveness":58,"demand":1,"length":9,"created":"","expires":"","registrar":null,"sectors":"Healthcare"},{"domain":"seven.info","status":"resell","attractiveness":58,"demand":35,"length":5,"created":"2006-12-13T09:35:53.000Z","expires":"2025-12-13T09:35:53.000Z","registrar":"Dynadot Inc","sectors":"Mathematics"},{"domain":"abandoned.info","status":"resell","attractiveness":58,"demand":10,"length":9,"created":"2024-12-30T12:30:50.000Z","expires":"2025-12-30T12:30:50.000Z","registrar":"Alibaba Cloud Computing Ltd. d/b/a HiChina (www.net.cn)","sectors":"Construction,Real Estate"},{"domain":"sixtyone.info","status":"available","attractiveness":58,"demand":5,"length":9,"created":"","expires":"","registrar":null,"sectors":"Mathematics"},{"domain":"tetrad.info","status":"available","attractiveness":58,"demand":5,"length":6,"created":"","expires":"","registrar":null,"sectors":"Mathematics"},{"domain":"linear.info","status":"premium","attractiveness":58,"demand":22,"length":6,"created":"2013-04-26T10:05:09.000Z","expires":"2026-04-26T10:05:09.000Z","registrar":"Dynadot Inc","sectors":"Engineering,Mathematics,Science"},{"domain":"niner.info","status":"available","attractiveness":58,"demand":5,"length":5,"created":"","expires":"","registrar":null,"sectors":"Mathematics"},{"domain":"acetic.info","status":"available","attractiveness":58,"demand":1,"length":6,"created":"","expires":"","registrar":null,"sectors":"Food and Beverage,Science"},{"domain":"addible.info","status":"available","attractiveness":58,"demand":2,"length":7,"created":"","expires":"","registrar":null,"sectors":"Engineering,Mathematics,Science"},{"domain":"eighter.info","status":"available","attractiveness":58,"demand":2,"length":7,"created":"","expires":"","registrar":null,"sectors":"Mathematics"},{"domain":"accented.info","status":"available","attractiveness":58,"demand":3,"length":8,"created":"","expires":"","registrar":null,"sectors":"Arts,Entertainment"},{"domain":"alacarte.info","status":"resell","attractiveness":58,"demand":11,"length":10,"created":"2025-01-11T15:15:35.000Z","expires":"2026-01-11T15:15:35.000Z","registrar":"Sav.com, LLC - 46","sectors":"Food and Beverage"},{"domain":"adhoc.info","status":"resell","attractiveness":58,"demand":24,"length":6,"created":"2023-03-14T17:00:00.000Z","expires":"2027-03-14T17:00:00.000Z","registrar":"Netregistry Wholesale Pty Ltd","sectors":"Business,Engineering,Technology"},{"domain":"adjustive.info","status":"available","attractiveness":58,"demand":1,"length":9,"created":"","expires":"","registrar":null,"sectors":"Manufacturing,Retail,Technology"},{"domain":"ache.info","status":"resell","attractiveness":58,"demand":7,"length":4,"created":"2017-11-29T10:11:05.000Z","expires":"2025-11-29T10:11:05.000Z","registrar":"Dynadot Inc","sectors":"Healthcare"},{"domain":"offhanded.info","status":"available","attractiveness":58,"demand":1,"length":9,"created":"","expires":"","registrar":null,"sectors":"Entertainment"},{"domain":"centesimal.info","status":"available","attractiveness":58,"demand":1,"length":10,"created":"","expires":"","registrar":null,"sectors":"Mathematics"},{"domain":"seventy.info","status":"resell","attractiveness":58,"demand":7,"length":7,"created":"2022-08-10T07:41:05.000Z","expires":"2026-08-10T07:41:05.000Z","registrar":"Sav.com, LLC","sectors":"Mathematics"},{"domain":"enwrapped.info","status":"available","attractiveness":58,"demand":0,"length":9,"created":"","expires":"","registrar":null,"sectors":"Entertainment,Fashion,Media"},{"domain":"lxxviii.info","status":"available","attractiveness":58,"demand":1,"length":7,"created":"","expires":"","registrar":null,"sectors":"Mathematics"},{"domain":"admittable.info","status":"available","attractiveness":56,"demand":1,"length":10,"created":"","expires":"","registrar":null,"sectors":"Education,Healthcare,Hospitality"},{"domain":"xxxvi.info","status":"available","attractiveness":56,"demand":1,"length":5,"created":"","expires":"","registrar":null,"sectors":"Mathematics"},{"domain":"xxxiv.info","status":"available","attractiveness":56,"demand":1,"length":5,"created":"","expires":"","registrar":null,"sectors":"Mathematics"},{"domain":"xxxvii.info","status":"available","attractiveness":56,"demand":2,"length":6,"created":"","expires":"","registrar":null,"sectors":"Mathematics"},{"domain":"xlviii.info","status":"available","attractiveness":56,"demand":1,"length":6,"created":"","expires":"","registrar":null,"sectors":"Mathematics"},{"domain":"fortynine.info","status":"available","attractiveness":56,"demand":3,"length":10,"created":"","expires":"","registrar":null,"sectors":"Mathematics"},{"domain":"xxviii.info","status":"available","attractiveness":56,"demand":1,"length":6,"created":"","expires":"","registrar":null,"sectors":"Mathematics"},{"domain":"liii.info","status":"available","attractiveness":56,"demand":4,"length":4,"created":"","expires":"","registrar":null,"sectors":"Mathematics"},{"domain":"accoutered.info","status":"available","attractiveness":56,"demand":0,"length":10,"created":"","expires":"","registrar":null,"sectors":"Fashion,Manufacturing,Retail"},{"domain":"xxiii.info","status":"available","attractiveness":56,"demand":4,"length":5,"created":"","expires":"","registrar":null,"sectors":"Mathematics"},{"domain":"xliv.info","status":"available","attractiveness":56,"demand":3,"length":4,"created":"","expires":"","registrar":null,"sectors":"Mathematics"},{"domain":"xlii.info","status":"available","attractiveness":56,"demand":5,"length":4,"created":"","expires":"","registrar":null,"sectors":"Mathematics"},{"domain":"xxvii.info","status":"available","attractiveness":56,"demand":3,"length":5,"created":"","expires":"","registrar":null,"sectors":"Mathematics"},{"domain":"halfdozen.info","status":"available","attractiveness":56,"demand":1,"length":10,"created":"","expires":"","registrar":null,"sectors":"Mathematics"},{"domain":"admittible.info","status":"available","attractiveness":56,"demand":1,"length":10,"created":"","expires":"","registrar":null,"sectors":"Education,Healthcare,Hospitality"},{"domain":"fiftynine.info","status":"available","attractiveness":56,"demand":4,"length":10,"created":"","expires":"","registrar":null,"sectors":"Mathematics"},{"domain":"xxxii.info","status":"available","attractiveness":56,"demand":1,"length":5,"created":"","expires":"","registrar":null,"sectors":"Mathematics"},{"domain":"fiftyfive.info","status":"available","attractiveness":56,"demand":8,"length":10,"created":"","expires":"","registrar":null,"sectors":"Mathematics"},{"domain":"xliii.info","status":"available","attractiveness":56,"demand":1,"length":5,"created":"","expires":"","registrar":null,"sectors":"Mathematics"},{"domain":"xxix.info","status":"available","attractiveness":56,"demand":4,"length":4,"created":"","expires":"","registrar":null,"sectors":"Mathematics"},{"domain":"fortytwo.info","status":"resell","attractiveness":56,"demand":17,"length":9,"created":"2024-07-28T17:01:32.000Z","expires":"2026-07-28T17:01:32.000Z","registrar":"Sav.com, LLC","sectors":"Mathematics"},{"domain":"thirtysix.info","status":"available","attractiveness":56,"demand":5,"length":10,"created":"","expires":"","registrar":null,"sectors":"Mathematics"},{"domain":"fiftytwo.info","status":"resell","attractiveness":56,"demand":6,"length":9,"created":"2024-12-30T14:56:52.000Z","expires":"2025-12-30T14:56:52.000Z","registrar":"Alibaba Cloud Computing Ltd. d/b/a HiChina (www.net.cn)","sectors":"Mathematics"},{"domain":"thirtytwo.info","status":"available","attractiveness":56,"demand":4,"length":10,"created":"","expires":"","registrar":null,"sectors":"Mathematics"},{"domain":"maledict.info","status":"available","attractiveness":56,"demand":1,"length":8,"created":"","expires":"","registrar":null,"sectors":"Religion"},{"domain":"thirtyone.info","status":"available","attractiveness":56,"demand":4,"length":10,"created":"","expires":"","registrar":null,"sectors":"Mathematics"},{"domain":"lvi.info","status":"resell","attractiveness":56,"demand":8,"length":3,"created":"2025-01-02T15:15:51.000Z","expires":"2026-01-02T15:15:51.000Z","registrar":"Sav.com, LLC - 33","sectors":"Mathematics"},{"domain":"xxxv.info","status":"available","attractiveness":56,"demand":4,"length":4,"created":"","expires":"","registrar":null,"sectors":"Mathematics"},{"domain":"addled.info","status":"available","attractiveness":56,"demand":2,"length":6,"created":"","expires":"","registrar":null,"sectors":"Entertainment"},{"domain":"lviii.info","status":"available","attractiveness":56,"demand":1,"length":5,"created":"","expires":"","registrar":null,"sectors":"Mathematics"},{"domain":"potbellied.info","status":"available","attractiveness":56,"demand":0,"length":10,"created":"","expires":"","registrar":null,"sectors":"Health and Fitness,Medicine"},{"domain":"abeyant.info","status":"available","attractiveness":56,"demand":1,"length":7,"created":"","expires":"","registrar":null,"sectors":"Business,Law"},{"domain":"xxxviii.info","status":"available","attractiveness":56,"demand":1,"length":7,"created":"","expires":"","registrar":null,"sectors":"Mathematics"},{"domain":"lii.info","status":"resell","attractiveness":56,"demand":7,"length":3,"created":"2001-11-15T13:49:16.000Z","expires":"2025-11-15T13:49:16.000Z","registrar":"Dynadot Inc","sectors":"Mathematics"},{"domain":"xxxiii.info","status":"available","attractiveness":56,"demand":2,"length":6,"created":"","expires":"","registrar":null,"sectors":"Mathematics"},{"domain":"lvii.info","status":"available","attractiveness":56,"demand":2,"length":4,"created":"","expires":"","registrar":null,"sectors":"Mathematics"},{"domain":"aone.info","status":"resell","attractiveness":56,"demand":15,"length":5,"created":"2025-06-21T15:15:38.000Z","expires":"2026-06-21T15:15:38.000Z","registrar":"Sav.com, LLC - 31","sectors":"Food and Beverage"},{"domain":"triad.info","status":"resell","attractiveness":56,"demand":15,"length":5,"created":"2024-03-18T17:00:01.000Z","expires":"2026-03-18T17:00:01.000Z","registrar":"Netregistry Wholesale Pty Ltd","sectors":"Arts"},{"domain":"fiftysix.info","status":"available","attractiveness":56,"demand":4,"length":9,"created":"","expires":"","registrar":null,"sectors":"Mathematics"},{"domain":"xxiv.info","status":"available","attractiveness":56,"demand":5,"length":4,"created":"","expires":"","registrar":null,"sectors":"Mathematics"},{"domain":"abdominous.info","status":"available","attractiveness":56,"demand":0,"length":10,"created":"","expires":"","registrar":null,"sectors":"Health and Fitness,Medicine"},{"domain":"fortyone.info","status":"available","attractiveness":56,"demand":5,"length":9,"created":"","expires":"","registrar":null,"sectors":"Mathematics"},{"domain":"appressed.info","status":"available","attractiveness":56,"demand":0,"length":9,"created":"","expires":"","registrar":null,"sectors":"Agriculture,Manufacturing,Retail"},{"domain":"admissive.info","status":"available","attractiveness":56,"demand":1,"length":9,"created":"","expires":"","registrar":null,"sectors":"Education,Healthcare,Hospitality"},{"domain":"xlvii.info","status":"available","attractiveness":56,"demand":2,"length":5,"created":"","expires":"","registrar":null,"sectors":"Mathematics"},{"domain":"aboral.info","status":"available","attractiveness":54,"demand":2,"length":6,"created":"","expires":"","registrar":null,"sectors":"Science"},{"domain":"adducent.info","status":"available","attractiveness":54,"demand":1,"length":8,"created":"","expires":"","registrar":null,"sectors":"Engineering,Mathematics,Science"},{"domain":"accentual.info","status":"available","attractiveness":54,"demand":3,"length":9,"created":"","expires":"","registrar":null,"sectors":"Arts,Entertainment"},{"domain":"viii.info","status":"resell","attractiveness":54,"demand":6,"length":4,"created":"2024-12-30T11:55:00.000Z","expires":"2025-12-30T11:55:00.000Z","registrar":"Alibaba Cloud Computing Ltd. d/b/a HiChina (www.net.cn)","sectors":"Mathematics"},{"domain":"actuated.info","status":"available","attractiveness":54,"demand":2,"length":8,"created":"","expires":"","registrar":null,"sectors":"Automotive,Manufacturing,Technology"},{"domain":"acoustical.info","status":"available","attractiveness":54,"demand":4,"length":10,"created":"","expires":"","registrar":null,"sectors":"Science"},{"domain":"topnotch.info","status":"resell","attractiveness":54,"demand":18,"length":8,"created":"2024-10-07T17:00:01.000Z","expires":"2025-10-07T17:00:01.000Z","registrar":"Sav.com, LLC - 16","sectors":"Business"},{"domain":"quintuplet.info","status":"available","attractiveness":54,"demand":1,"length":10,"created":"","expires":"","registrar":null,"sectors":"Healthcare,Medicine,Science"},{"domain":"vii.info","status":"resell","attractiveness":54,"demand":13,"length":3,"created":"2017-05-08T10:06:02.000Z","expires":"2026-05-08T10:06:02.000Z","registrar":"Key-Systems GmbH","sectors":"Mathematics"},{"domain":"adductive.info","status":"available","attractiveness":54,"demand":0,"length":9,"created":"","expires":"","registrar":null,"sectors":"Engineering,Mathematics,Science"},{"domain":"abhorrent.info","status":"available","attractiveness":54,"demand":1,"length":9,"created":"","expires":"","registrar":null,"sectors":"Humanities"},{"domain":"adjuratory.info","status":"available","attractiveness":54,"demand":0,"length":10,"created":"","expires":"","registrar":null,"sectors":"Law,Politics,Religion"},{"domain":"abatic.info","status":"available","attractiveness":54,"demand":1,"length":6,"created":"","expires":"","registrar":null,"sectors":"Science"},{"domain":"quadruplet.info","status":"available","attractiveness":54,"demand":1,"length":10,"created":"","expires":"","registrar":null,"sectors":"Healthcare,Medicine,Science"},{"domain":"monitory.info","status":"available","attractiveness":54,"demand":3,"length":8,"created":"","expires":"","registrar":null,"sectors":"Business,Education,Healthcare"},{"domain":"abatable.info","status":"available","attractiveness":54,"demand":1,"length":8,"created":"","expires":"","registrar":null,"sectors":"Law"},{"domain":"admonitory.info","status":"available","attractiveness":54,"demand":0,"length":10,"created":"","expires":"","registrar":null,"sectors":"Business,Education,Healthcare"},{"domain":"accursed.info","status":"available","attractiveness":54,"demand":3,"length":8,"created":"","expires":"","registrar":null,"sectors":"Entertainment,Media,Religion"},{"domain":"deserted.info","status":"available","attractiveness":54,"demand":3,"length":8,"created":"","expires":"","registrar":null,"sectors":"Hospitality,Real Estate"},{"domain":"abasic.info","status":"available","attractiveness":54,"demand":1,"length":6,"created":"","expires":"","registrar":null,"sectors":"Science"},{"domain":"deuceace.info","status":"available","attractiveness":54,"demand":1,"length":9,"created":"","expires":"","registrar":null,"sectors":"Sports"},{"domain":"achy.info","status":"available","attractiveness":54,"demand":3,"length":4,"created":"","expires":"","registrar":null,"sectors":"Healthcare"},{"domain":"abient.info","status":"available","attractiveness":54,"demand":1,"length":6,"created":"","expires":"","registrar":null,"sectors":"Science"},{"domain":"abaxial.info","status":"available","attractiveness":54,"demand":1,"length":7,"created":"","expires":"","registrar":null,"sectors":"Science"},{"domain":"scratchy.info","status":"available","attractiveness":54,"demand":3,"length":8,"created":"","expires":"","registrar":null,"sectors":"Fashion"},{"domain":"adaxial.info","status":"available","attractiveness":54,"demand":2,"length":7,"created":"","expires":"","registrar":null,"sectors":"Science"},{"domain":"quatern.info","status":"available","attractiveness":54,"demand":2,"length":7,"created":"","expires":"","registrar":null,"sectors":"Mathematics"},{"domain":"abducens.info","status":"available","attractiveness":54,"demand":1,"length":8,"created":"","expires":"","registrar":null,"sectors":"Medicine"},{"domain":"adducting.info","status":"available","attractiveness":54,"demand":1,"length":9,"created":"","expires":"","registrar":null,"sectors":"Engineering,Mathematics,Science"},{"domain":"achromatic.info","status":"available","attractiveness":54,"demand":4,"length":10,"created":"","expires":"","registrar":null,"sectors":"Science"},{"domain":"adpressed.info","status":"available","attractiveness":54,"demand":0,"length":9,"created":"","expires":"","registrar":null,"sectors":"Agriculture,Manufacturing,Retail"},{"domain":"iii.info","status":"resell","attractiveness":54,"demand":24,"length":3,"created":"2002-07-13T19:24:39.000Z","expires":"2026-07-13T19:24:39.000Z","registrar":"Megazone Corp., dba HOSTING.KR","sectors":"Mathematics"},{"domain":"septet.info","status":"available","attractiveness":53,"demand":1,"length":6,"created":"","expires":"","registrar":null,"sectors":"General"},{"domain":"xxx.info","status":"available","attractiveness":53,"demand":30,"length":3,"created":"","expires":"","registrar":null,"sectors":"Arts,Entertainment,Media"},{"domain":"sestet.info","status":"available","attractiveness":53,"demand":1,"length":6,"created":"","expires":"","registrar":null,"sectors":"Arts"},{"domain":"abysmal.info","status":"available","attractiveness":52,"demand":4,"length":7,"created":"","expires":"","registrar":null,"sectors":"Arts,Entertainment,Media"},{"domain":"ninetysix.info","status":"available","attractiveness":52,"demand":4,"length":10,"created":"","expires":"","registrar":null,"sectors":"Mathematics"},{"domain":"uphill.info","status":"resell","attractiveness":52,"demand":7,"length":6,"created":"2025-04-20T21:08:45.000Z","expires":"2026-04-20T21:08:45.000Z","registrar":"Mesh Digital Limited","sectors":"Sports,Transportation,Travel"},{"domain":"lxxi.info","status":"available","attractiveness":52,"demand":2,"length":4,"created":"","expires":"","registrar":null,"sectors":"Mathematics"},{"domain":"chagrined.info","status":"available","attractiveness":52,"demand":1,"length":9,"created":"","expires":"","registrar":null,"sectors":"Humanities"},{"domain":"lxiv.info","status":"available","attractiveness":52,"demand":3,"length":4,"created":"","expires":"","registrar":null,"sectors":"Mathematics"},{"domain":"lxxxiv.info","status":"available","attractiveness":52,"demand":1,"length":6,"created":"","expires":"","registrar":null,"sectors":"Mathematics"},{"domain":"xciv.info","status":"available","attractiveness":52,"demand":2,"length":4,"created":"","expires":"","registrar":null,"sectors":"Mathematics"},{"domain":"sixtysix.info","status":"resell","attractiveness":52,"demand":5,"length":9,"created":"2024-12-30T15:00:36.000Z","expires":"2025-12-30T15:00:36.000Z","registrar":"Alibaba Cloud Computing Ltd. d/b/a HiChina (www.net.cn)","sectors":"Mathematics"},{"domain":"repulsive.info","status":"available","attractiveness":52,"demand":1,"length":9,"created":"","expires":"","registrar":null,"sectors":"Humanities"},{"domain":"eightyone.info","status":"available","attractiveness":52,"demand":3,"length":10,"created":"","expires":"","registrar":null,"sectors":"Mathematics"},{"domain":"lxvi.info","status":"available","attractiveness":52,"demand":3,"length":4,"created":"","expires":"","registrar":null,"sectors":"Mathematics"},{"domain":"repugnant.info","status":"available","attractiveness":52,"demand":1,"length":9,"created":"","expires":"","registrar":null,"sectors":"Humanities"},{"domain":"lxxiii.info","status":"available","attractiveness":52,"demand":2,"length":6,"created":"","expires":"","registrar":null,"sectors":"Mathematics"},{"domain":"lxxvii.info","status":"available","attractiveness":52,"demand":2,"length":6,"created":"","expires":"","registrar":null,"sectors":"Mathematics"},{"domain":"adenoidal.info","status":"available","attractiveness":52,"demand":1,"length":9,"created":"","expires":"","registrar":null,"sectors":"Health and Fitness,Medicine,Science"},{"domain":"sixtytwo.info","status":"available","attractiveness":52,"demand":3,"length":9,"created":"","expires":"","registrar":null,"sectors":"Mathematics"},{"domain":"abominable.info","status":"available","attractiveness":52,"demand":2,"length":10,"created":"","expires":"","registrar":null,"sectors":"Entertainment,Humanities"},{"domain":"littlejoe.info","status":"available","attractiveness":52,"demand":2,"length":10,"created":"","expires":"","registrar":null,"sectors":"Entertainment,Media"},{"domain":"xcvi.info","status":"available","attractiveness":52,"demand":2,"length":4,"created":"","expires":"","registrar":null,"sectors":"Mathematics"},{"domain":"eightytwo.info","status":"available","attractiveness":52,"demand":4,"length":10,"created":"","expires":"","registrar":null,"sectors":"Mathematics"},{"domain":"sixtyfour.info","status":"available","attractiveness":52,"demand":4,"length":10,"created":"","expires":"","registrar":null,"sectors":"Mathematics"},{"domain":"lxxxiii.info","status":"available","attractiveness":52,"demand":1,"length":7,"created":"","expires":"","registrar":null,"sectors":"Mathematics"},{"domain":"aboulic.info","status":"available","attractiveness":52,"demand":1,"length":7,"created":"","expires":"","registrar":null,"sectors":"Medicine"},{"domain":"lxxxi.info","status":"available","attractiveness":52,"demand":1,"length":5,"created":"","expires":"","registrar":null,"sectors":"Mathematics"},{"domain":"xci.info","status":"available","attractiveness":52,"demand":4,"length":3,"created":"","expires":"","registrar":null,"sectors":"Mathematics"},{"domain":"lxxxvii.info","status":"available","attractiveness":52,"demand":1,"length":7,"created":"","expires":"","registrar":null,"sectors":"Mathematics"},{"domain":"tierce.info","status":"available","attractiveness":52,"demand":3,"length":6,"created":"","expires":"","registrar":null,"sectors":"General"},{"domain":"lxxvi.info","status":"available","attractiveness":52,"demand":1,"length":5,"created":"","expires":"","registrar":null,"sectors":"Mathematics"},{"domain":"ixl.info","status":"available","attractiveness":52,"demand":9,"length":3,"created":"","expires":"","registrar":null,"sectors":"Mathematics"},{"domain":"lxxiv.info","status":"available","attractiveness":52,"demand":1,"length":5,"created":"","expires":"","registrar":null,"sectors":"Mathematics"},{"domain":"lxxxii.info","status":"available","attractiveness":52,"demand":1,"length":6,"created":"","expires":"","registrar":null,"sectors":"Mathematics"},{"domain":"lxii.info","status":"available","attractiveness":52,"demand":2,"length":4,"created":"","expires":"","registrar":null,"sectors":"Mathematics"},{"domain":"detestable.info","status":"available","attractiveness":52,"demand":1,"length":10,"created":"","expires":"","registrar":null,"sectors":"Humanities"},{"domain":"ixc.info","status":"available","attractiveness":52,"demand":5,"length":3,"created":"","expires":"","registrar":null,"sectors":"Mathematics"},{"domain":"xcii.info","status":"available","attractiveness":52,"demand":2,"length":4,"created":"","expires":"","registrar":null,"sectors":"Mathematics"},{"domain":"lxxii.info","status":"available","attractiveness":52,"demand":1,"length":5,"created":"","expires":"","registrar":null,"sectors":"Mathematics"},{"domain":"xcviii.info","status":"available","attractiveness":52,"demand":1,"length":6,"created":"","expires":"","registrar":null,"sectors":"Mathematics"},{"domain":"abusive.info","status":"available","attractiveness":52,"demand":3,"length":7,"created":"","expires":"","registrar":null,"sectors":"Healthcare,Law"},{"domain":"lxxv.info","status":"available","attractiveness":52,"demand":2,"length":4,"created":"","expires":"","registrar":null,"sectors":"Mathematics"},{"domain":"lxxxv.info","status":"available","attractiveness":52,"demand":1,"length":5,"created":"","expires":"","registrar":null,"sectors":"Mathematics"},{"domain":"lxvii.info","status":"available","attractiveness":52,"demand":1,"length":5,"created":"","expires":"","registrar":null,"sectors":"Mathematics"},{"domain":"lxviii.info","status":"available","attractiveness":52,"demand":2,"length":6,"created":"","expires":"","registrar":null,"sectors":"Mathematics"},{"domain":"xcvii.info","status":"available","attractiveness":52,"demand":1,"length":5,"created":"","expires":"","registrar":null,"sectors":"Mathematics"},{"domain":"ablated.info","status":"available","attractiveness":52,"demand":1,"length":7,"created":"","expires":"","registrar":null,"sectors":"Science"},{"domain":"lxxxvi.info","status":"available","attractiveness":52,"demand":1,"length":6,"created":"","expires":"","registrar":null,"sectors":"Mathematics"},{"domain":"odious.info","status":"available","attractiveness":52,"demand":2,"length":6,"created":"","expires":"","registrar":null,"sectors":"Entertainment,Humanities"},{"domain":"sixtyfive.info","status":"available","attractiveness":52,"demand":3,"length":10,"created":"","expires":"","registrar":null,"sectors":"Mathematics"},{"domain":"xciii.info","status":"available","attractiveness":52,"demand":1,"length":5,"created":"","expires":"","registrar":null,"sectors":"Mathematics"},{"domain":"decumbent.info","status":"available","attractiveness":52,"demand":1,"length":9,"created":"","expires":"","registrar":null,"sectors":"Healthcare,Medicine,Science"},{"domain":"ninetyone.info","status":"available","attractiveness":52,"demand":5,"length":10,"created":"","expires":"","registrar":null,"sectors":"Mathematics"},{"domain":"triplet.info","status":"resell","attractiveness":50,"demand":8,"length":7,"created":"2024-12-30T11:46:19.000Z","expires":"2025-12-30T11:46:19.000Z","registrar":"Alibaba Cloud Computing Ltd. d/b/a HiChina (www.net.cn)","sectors":"Science"},{"domain":"aborticide.info","status":"available","attractiveness":50,"demand":0,"length":10,"created":"","expires":"","registrar":null,"sectors":"Medicine"},{"domain":"trine.info","status":"resell","attractiveness":50,"demand":11,"length":5,"created":"2025-01-15T15:15:16.000Z","expires":"2026-01-15T15:15:16.000Z","registrar":"Sav.com, LLC - 18","sectors":"General,Religion"},{"domain":"cinque.info","status":"available","attractiveness":50,"demand":7,"length":6,"created":"","expires":"","registrar":null,"sectors":"Mathematics"},{"domain":"ogdoad.info","status":"available","attractiveness":50,"demand":1,"length":6,"created":"","expires":"","registrar":null,"sectors":"Mathematics"},{"domain":"needlelike.info","status":"available","attractiveness":50,"demand":0,"length":10,"created":"","expires":"","registrar":null,"sectors":"Engineering,Medicine,Science"},{"domain":"abdicable.info","status":"available","attractiveness":50,"demand":0,"length":9,"created":"","expires":"","registrar":null,"sectors":"Law"},{"domain":"adhominem.info","status":"available","attractiveness":50,"demand":2,"length":10,"created":"","expires":"","registrar":null,"sectors":"Humanities,Law,Politics"},{"domain":"acerb.info","status":"available","attractiveness":50,"demand":2,"length":5,"created":"","expires":"","registrar":null,"sectors":"Science"},{"domain":"quint.info","status":"resell","attractiveness":50,"demand":13,"length":5,"created":"2025-06-19T15:15:53.000Z","expires":"2026-06-19T15:15:53.000Z","registrar":"Sav.com, LLC - 5","sectors":"Arts,Entertainment"},{"domain":"abducting.info","status":"available","attractiveness":50,"demand":0,"length":9,"created":"","expires":"","registrar":null,"sectors":"Medicine"},{"domain":"acetous.info","status":"available","attractiveness":50,"demand":1,"length":7,"created":"","expires":"","registrar":null,"sectors":"Science"},{"domain":"abranchial.info","status":"available","attractiveness":50,"demand":0,"length":10,"created":"","expires":"","registrar":null,"sectors":"Science"},{"domain":"abbatial.info","status":"available","attractiveness":50,"demand":0,"length":8,"created":"","expires":"","registrar":null,"sectors":"Religion"},{"domain":"broached.info","status":"available","attractiveness":50,"demand":0,"length":8,"created":"","expires":"","registrar":null,"sectors":"Food and Beverage"},{"domain":"acerbic.info","status":"available","attractiveness":50,"demand":2,"length":7,"created":"","expires":"","registrar":null,"sectors":"Arts,Humanities,Media"},{"domain":"spinous.info","status":"available","attractiveness":50,"demand":1,"length":7,"created":"","expires":"","registrar":null,"sectors":"Agriculture,Science"},{"domain":"abactinal.info","status":"available","attractiveness":50,"demand":0,"length":9,"created":"","expires":"","registrar":null,"sectors":"Science"},{"domain":"acapnic.info","status":"available","attractiveness":50,"demand":0,"length":7,"created":"","expires":"","registrar":null,"sectors":"Healthcare,Medicine,Science"},{"domain":"acapnotic.info","status":"available","attractiveness":50,"demand":0,"length":9,"created":"","expires":"","registrar":null,"sectors":"Healthcare,Medicine,Science"},{"domain":"adactylous.info","status":"available","attractiveness":50,"demand":0,"length":10,"created":"","expires":"","registrar":null,"sectors":"Science"},{"domain":"acquitted.info","status":"available","attractiveness":50,"demand":1,"length":9,"created":"","expires":"","registrar":null,"sectors":"Law"},{"domain":"gillless.info","status":"available","attractiveness":50,"demand":0,"length":9,"created":"","expires":"","registrar":null,"sectors":"Science"},{"domain":"acellular.info","status":"available","attractiveness":50,"demand":1,"length":9,"created":"","expires":"","registrar":null,"sectors":"Science"},{"domain":"lxx.info","status":"available","attractiveness":50,"demand":5,"length":3,"created":"","expires":"","registrar":null,"sectors":"Mathematics"},{"domain":"abomasal.info","status":"available","attractiveness":50,"demand":0,"length":8,"created":"","expires":"","registrar":null,"sectors":"Agriculture"},{"domain":"vinegary.info","status":"available","attractiveness":50,"demand":1,"length":8,"created":"","expires":"","registrar":null,"sectors":"Food and Beverage"},{"domain":"acetose.info","status":"available","attractiveness":50,"demand":1,"length":7,"created":"","expires":"","registrar":null,"sectors":"Science"},{"domain":"scummy.info","status":"available","attractiveness":50,"demand":1,"length":6,"created":"","expires":"","registrar":null,"sectors":"Humanities"},{"domain":"aculeated.info","status":"available","attractiveness":50,"demand":0,"length":9,"created":"","expires":"","registrar":null,"sectors":"Engineering,Medicine,Science"},{"domain":"acerose.info","status":"available","attractiveness":50,"demand":1,"length":7,"created":"","expires":"","registrar":null,"sectors":"Science"},{"domain":"ilxx.info","status":"available","attractiveness":48,"demand":1,"length":4,"created":"","expires":"","registrar":null,"sectors":"Mathematics"},{"domain":"notguilty.info","status":"available","attractiveness":48,"demand":5,"length":10,"created":"","expires":"","registrar":null,"sectors":"Law"},{"domain":"ilxxx.info","status":"available","attractiveness":48,"demand":1,"length":5,"created":"","expires":"","registrar":null,"sectors":"Mathematics"},{"domain":"lxxxviii.info","status":"available","attractiveness":48,"demand":1,"length":8,"created":"","expires":"","registrar":null,"sectors":"Mathematics"},{"domain":"execrable.info","status":"available","attractiveness":48,"demand":0,"length":9,"created":"","expires":"","registrar":null,"sectors":"Entertainment,Humanities"},{"domain":"acanthotic.info","status":"available","attractiveness":46,"demand":0,"length":10,"created":"","expires":"","registrar":null,"sectors":"Agriculture,Science"},{"domain":"acarpous.info","status":"available","attractiveness":46,"demand":0,"length":8,"created":"","expires":"","registrar":null,"sectors":"Agriculture,Science"},{"domain":"acanthous.info","status":"available","attractiveness":46,"demand":0,"length":9,"created":"","expires":"","registrar":null,"sectors":"Agriculture,Science"},{"domain":"achromic.info","status":"available","attractiveness":46,"demand":2,"length":8,"created":"","expires":"","registrar":null,"sectors":"Science"},{"domain":"acetabular.info","status":"available","attractiveness":46,"demand":1,"length":10,"created":"","expires":"","registrar":null,"sectors":"Science"},{"domain":"acephalous.info","status":"available","attractiveness":46,"demand":1,"length":10,"created":"","expires":"","registrar":null,"sectors":"Science"},{"domain":"acaudate.info","status":"available","attractiveness":46,"demand":1,"length":8,"created":"","expires":"","registrar":null,"sectors":"Agriculture,Science"},{"domain":"theabsurd.info","status":"available","attractiveness":46,"demand":1,"length":10,"created":"","expires":"","registrar":null,"sectors":"Arts,Entertainment,Media"},{"domain":"acanthoid.info","status":"available","attractiveness":46,"demand":1,"length":9,"created":"","expires":"","registrar":null,"sectors":"Agriculture,Science"},{"domain":"acheronian.info","status":"available","attractiveness":46,"demand":1,"length":10,"created":"","expires":"","registrar":null,"sectors":"Humanities"},{"domain":"achromous.info","status":"available","attractiveness":46,"demand":1,"length":9,"created":"","expires":"","registrar":null,"sectors":"Science"},{"domain":"acarpelous.info","status":"available","attractiveness":46,"demand":0,"length":10,"created":"","expires":"","registrar":null,"sectors":"Agriculture,Science"},{"domain":"stripling.info","status":"available","attractiveness":46,"demand":2,"length":9,"created":"","expires":"","registrar":null,"sectors":"Education,Entertainment,Healthcare"},{"domain":"acapnial.info","status":"available","attractiveness":46,"demand":0,"length":8,"created":"","expires":"","registrar":null,"sectors":"Healthcare,Medicine,Science"},{"domain":"achenial.info","status":"available","attractiveness":46,"demand":1,"length":8,"created":"","expires":"","registrar":null,"sectors":"Science"},{"domain":"quaternary.info","status":"available","attractiveness":46,"demand":3,"length":10,"created":"","expires":"","registrar":null,"sectors":"Mathematics"},{"domain":"acetylenic.info","status":"available","attractiveness":46,"demand":1,"length":10,"created":"","expires":"","registrar":null,"sectors":"Science"},{"domain":"vinegarish.info","status":"available","attractiveness":46,"demand":1,"length":10,"created":"","expires":"","registrar":null,"sectors":"Food and Beverage"},{"domain":"acicular.info","status":"available","attractiveness":46,"demand":2,"length":8,"created":"","expires":"","registrar":null,"sectors":"Science"},{"domain":"acetylic.info","status":"available","attractiveness":46,"demand":1,"length":8,"created":"","expires":"","registrar":null,"sectors":"Science"},{"domain":"stemless.info","status":"available","attractiveness":46,"demand":2,"length":8,"created":"","expires":"","registrar":null,"sectors":"Agriculture,Science"},{"domain":"cotyloid.info","status":"available","attractiveness":46,"demand":1,"length":8,"created":"","expires":"","registrar":null,"sectors":"Science"},{"domain":"accusatory.info","status":"available","attractiveness":44,"demand":1,"length":10,"created":"","expires":"","registrar":null,"sectors":"Law"},{"domain":"cotyloidal.info","status":"available","attractiveness":44,"demand":1,"length":10,"created":"","expires":"","registrar":null,"sectors":"Science"},{"domain":"acherontic.info","status":"available","attractiveness":44,"demand":1,"length":10,"created":"","expires":"","registrar":null,"sectors":"Humanities"},{"domain":"abscessed.info","status":"available","attractiveness":41,"demand":0,"length":9,"created":"","expires":"","registrar":null,"sectors":"Healthcare"},{"domain":"accusive.info","status":"available","attractiveness":40,"demand":1,"length":8,"created":"","expires":"","registrar":null,"sectors":"Law"},{"domain":"accurst.info","status":"available","attractiveness":40,"demand":1,"length":7,"created":"","expires":"","registrar":null,"sectors":"Religion"},{"domain":"scurrilous.info","status":"available","attractiveness":40,"demand":1,"length":10,"created":"","expires":"","registrar":null,"sectors":"Entertainment,Media,Politics"}]